{
  "name": "maplocs",
  "description": "Wuthering Waves Map Locations Dataset",
  "version": "1.1.0",
  "latestAdd": {},
  "author": "MGSimard - https://github.com/MGSimard/",
  "data": [
    {
      "region": "Central Plains",
      "pos": [-42.68, 24.85],
      "subregions": [
        { "name": "Gubei Pass", "pos": [-19.24, -6.33] },
        { "name": "Lake Deerslumber", "pos": [-115.95, -19.13] },
        { "name": "Loong's Gaze Suburbs", "pos": [-79.46, -1.31] },
        { "name": "Qichi Village", "pos": [-29.97, 19.93] },
        { "name": "Stone Pile Plain", "pos": [-52.16, -19.0] },
        { "name": "Taoyuan Vale", "pos": [-42.29, -6.51] },
        { "name": "Tiderise Cliff", "pos": [-32.87, 50.06] },
        { "name": "Tower of Adversity", "pos": [-66.66, 99.66] },
        { "name": "Yeming Slide", "pos": [-90.1, -31.09] }
      ],
      "nexuses": [
        [-22.25, 22.65],
        [-59.3, 84.98]
      ],
      "beacons": [
        [-105.85, -8.9],
        [-96, 7],
        [-87.7, -29.8],
        [-70.3, -11.4],
        [-33.28, -20.65],
        [-32.95, -1.7],
        [-21.6, 2],
        [-50.1, 11.9],
        [-51.95, 30.65],
        [-55.15, 54.6],
        [-34.75, 57.35],
        [-33.25, 34.95],
        [-16.5, 50.9]
      ],
      "bosses": [
        {
          "name": "Chaotic Juncture: Ember",
          "pos": [-32.25, 23.5],
          "rewards": [
            "Union EXP",
            "Unending Destruction",
            "Standard Weapon Mold",
            "Energy Core",
            "Sealed Tube",
            "Intimacy",
            "Shell Credit"
          ]
        },
        { "name": "Crownless", "pos": [-55, -18.9], "rewards": [] },
        { "name": "Tempest Mephis", "pos": [-23.4, 12.6], "rewards": [] }
      ],
      "tacet fields": [{ "pos": [-31.08, 18.78], "rewards": [] }],
      "tactical holograms": [],
      "forgery challenges": [{ "name": "Marigold Woods", "pos": [-96, -1.2], "rewards": [] }],
      "domains": [{ "name": "Parallel Perception", "pos": [-31.1, 39.85], "rewards": [] }],
      "misc": [{ "name": "Tower of Adversity", "pos": [-63.3, 98], "rewards": [] }]
    },
    {
      "region": "Desorock Highland",
      "pos": [12.9, 39.76],
      "subregions": [
        { "name": "Camp Overwatch", "pos": [41.75, 29.22] },
        { "name": "Misty Coast", "pos": [15.72, 67.47] },
        { "name": "Rearguard Base", "pos": [6.8, 42.03] },
        { "name": "Withering Frontline", "pos": [27.93, 43.89] }
      ],
      "nexuses": [[-3.6, 30.24]],
      "beacons": [
        [18.9, 81.6],
        [23, 60.64],
        [5.1, 48.9],
        [20.35, 29.9],
        [41.7, 21.5],
        [45.7, 39.9],
        [1.5, 8.5]
      ],
      "bosses": [
        { "name": "Impermanence Heron", "pos": [44.2, 33.2], "rewards": [] },
        { "name": "Thundering Mephis", "pos": [28, 40.2], "rewards": [] }
      ],
      "tacet fields": [
        { "pos": [7.08, 16], "rewards": [] },
        { "pos": [24.76, 77.03], "rewards": [] }
      ],
      "tactical holograms": [],
      "forgery challenges": [],
      "domains": [{ "name": "Perspective Bender", "pos": [37.2, 31.5], "rewards": [] }],
      "misc": []
    },
    {
      "region": "Dim Forest",
      "pos": [-205.18, 30.77],
      "subregions": [
        { "name": "Forbidden Forest", "pos": [-209.34, -3.2] },
        { "name": "Giant Banyan", "pos": [-230.41, 32.18] },
        { "name": "Thorny Passage", "pos": [-198.64, 34.9] },
        { "name": "Violet Banyan", "pos": [-199.95, 15.41] },
        { "name": "Wenye Beach", "pos": [-226.04, 63.0] }
      ],
      "nexuses": [[-219.38, 4.88]],
      "beacons": [
        [-238.8, 61.5],
        [-222.8, 58.2],
        [-210, 53.4],
        [-236.4, 39.25],
        [-221.8, 26.7],
        [-210.6, 30.2],
        [-188.6, 17.3],
        [-192.6, -6.2]
      ],
      "bosses": [{ "name": "Feilian Beringal", "pos": [-225.5, 31.4], "rewards": [] }],
      "tacet fields": [{ "pos": [-231.3, 5], "rewards": [] }],
      "tactical holograms": [{ "name": "Feilian Beringal", "pos": [-235.5, 66.2], "rewards": [] }],
      "forgery challenges": [
        { "name": "Misty Forest", "pos": [-199, -19.5], "rewards": [] },
        { "name": "Moonlit Groves", "pos": [-174, 36.9], "rewards": [] }
      ],
      "domains": [],
      "misc": []
    },
    {
      "region": "Gorges of Spirits",
      "pos": [-42, -32],
      "subregions": [
        { "name": "Bell-Borne Ravine", "pos": [-62.36, -50.68] },
        { "name": "Clouded Cliffs", "pos": [-37.2, -36.65] },
        { "name": "Memento Square", "pos": [-47.28, -33.47] }
      ],
      "nexuses": [[-32, -33.7]],
      "beacons": [
        [-53.3, -27.77],
        [-56.3, -38.1]
      ],
      "bosses": [{ "name": "Bell-Borne Geochelone", "pos": [-57.2, -50.3], "rewards": [] }],
      "tacet fields": [],
      "tactical holograms": [],
      "forgery challenges": [],
      "domains": [],
      "misc": []
    },
    {
      "region": "Jinzhou",
      "pos": [-81, 31],
      "subregions": [
        { "name": "Jinzhou", "pos": [-79.83, 30.61] },
        { "name": "Lake Heights", "pos": [-106.25, 28.07] },
        { "name": "Shade Ridge", "pos": [-99.12, 57.6] },
        { "name": "Sky Ray", "pos": [-113.21, 31.67] }
      ],
      "nexuses": [[-75.7, 27.1]],
      "beacons": [
        [-111, 44.75],
        [-105.45, 48.35],
        [-94.05, 54.47],
        [-96.6, 32],
        [-85.9, 31.4],
        [-74.8, 41.7],
        [-80.38, 18.15]
      ],
      "bosses": [],
      "tacet fields": [],
      "tactical holograms": [],
      "forgery challenges": [],
      "domains": [],
      "misc": [{ "name": "The Grand Library", "pos": [-95, 43.35], "rewards": [] }]
    },
    {
      "region": "Mt. Firmament",
      "pos": [-233.95, 250.46],
      "subregions": [
        { "name": "Hongzhen", "pos": [-235.54, 241.02] },
        { "name": "Loong's Crest", "pos": [-234.2, 276.16] },
        { "name": "Loong's Rest", "pos": [-223.32, 252.97] },
        { "name": "Loong's Ridge", "pos": [-269.12, 260.28] },
        { "name": "Luminous Shore", "pos": [-212.95, 203.58] },
        { "name": "Tianqu Tree", "pos": [-251.18, 257.24] },
        { "name": "Xuanji Ridges", "pos": [-246.71, 218.94] }
      ],
      "nexuses": [
        [-209.06, 195.82],
        [-231.5, 232.65]
      ],
      "beacons": [
        [-226.3, 215.1],
        [-239.2, 220.4],
        [-245.8, 230.2],
        [-252.7, 230.5],
        [-262.6, 240.1],
        [-239.85, 242.63],
        [-253.3, 256],
        [-265, 262.8],
        [-261.7, 271.5],
        [-246.1, 293.3],
        [-247.25, 279.9],
        [-240.4, 278.18],
        [-217.2, 281.8],
        [-234.3, 264.4],
        [-230.5, 266.4],
        [-222.8, 262.7],
        [-218.6, 247.4]
      ],
      "bosses": [{ "name": "Sentinel Jué", "pos": [-253.7, 283.1], "rewards": [] }],
      "tacet fields": [],
      "tactical holograms": [],
      "forgery challenges": [],
      "domains": [],
      "misc": []
    },
    {
      "region": "Norfall Barrens",
      "pos": [84.97, 109.54],
      "subregions": [
        { "name": "Norfall Pass", "pos": [56.19, 77.42] },
        { "name": "Suspended Ruins", "pos": [76.68, 117.94] }
      ],
      "nexuses": [],
      "beacons": [
        [57.1, 64.9],
        [48.3, 93],
        [67, 98.7],
        [86.7, 98.1],
        [57.2, 123.7]
      ],
      "bosses": [{ "name": "Statue of the Crownless: Heart", "pos": [83.2, 143], "rewards": [] }],
      "tacet fields": [],
      "tactical holograms": [],
      "forgery challenges": [],
      "domains": [],
      "misc": []
    },
    {
      "region": "Port City of Guixu",
      "pos": [-156.86, -33.75],
      "subregions": [
        { "name": "Donglu Research Station", "pos": [-144.39, -5.68] },
        { "name": "Nostalgia Isle", "pos": [-126.46, -45.35] },
        { "name": "Sea of Flames", "pos": [-155.95, -38.71] },
        { "name": "Settle Range", "pos": [-175.97, 10.54] }
      ],
      "nexuses": [[-151.9, 1]],
      "beacons": [
        [-172.9, 16],
        [-173.8, -15],
        [-160.5, -23.5],
        [-159.3, -37.4],
        [-128.6, -38.7],
        [-134.7, -12.5]
      ],
      "bosses": [{ "name": "Inferno Rider", "pos": [-156.7, -46.1], "rewards": [] }],
      "tacet fields": [{ "pos": [-167.65, 8.05], "rewards": [] }],
      "tactical holograms": [{ "name": "Tempest Mephis", "pos": [-183.65, 6.05], "rewards": [] }],
      "forgery challenges": [{ "name": "Flaming Remnants", "pos": [-151.35, -27.3], "rewards": [] }],
      "domains": [],
      "misc": []
    },
    {
      "region": "Tiger's Maw",
      "pos": [-136, 36],
      "subregions": [
        { "name": "Distribution Center", "pos": [-159.57, 34.74] },
        { "name": "Tiger's Maw Mine", "pos": [-135.7, 36.44] }
      ],
      "nexuses": [[-128.5, 24.9]],
      "beacons": [
        [-159.45, 40.55],
        [-142.5, 42.3],
        [-140, 47.8],
        [-136.4, 31.1]
      ],
      "bosses": [],
      "tacet fields": [],
      "tactical holograms": [],
      "forgery challenges": [],
      "domains": [],
      "misc": []
    },
    {
      "region": "Whining Aix's Mire",
      "pos": [-227.08, 99.02],
      "subregions": [
        { "name": "Court of Savantae Ruins", "pos": [-220.89, 117.77] },
        { "name": "Fallen Grave", "pos": [-237.18, 102.25] },
        { "name": "Frosting Harbor", "pos": [-220.93, 147.46] },
        { "name": "Lollo Warehouse", "pos": [-214.24, 73.63] },
        { "name": "Plateau Ruins", "pos": [-203.67, 102.16] },
        { "name": "Port Gunchao", "pos": [-185.43, 109.13] },
        { "name": "Waving Battlefield", "pos": [-200.42, 118.47] }
      ],
      "nexuses": [
        [-208, 86.15],
        [-185.14, 115.3]
      ],
      "beacons": [
        [-214, 143.5],
        [-192.8, 128],
        [-207.7, 120.6],
        [-227, 118.3],
        [-240.2, 128.6],
        [-243.45, 105.5],
        [-233.9, 88],
        [-218.4, 79.1],
        [-198.2, 74.2],
        [-215.2, 103.7],
        [-186.7, 94.93]
      ],
      "bosses": [
        { "name": "Mech Abomination", "pos": [-222, 123.75], "rewards": [] },
        { "name": "Mourning Aix", "pos": [-248.45, 114.25], "rewards": [] }
      ],
      "tacet fields": [{ "pos": [-189.2, 131.15], "rewards": [] }],
      "tactical holograms": [{ "name": "Mourning Aix", "pos": [-241.55, 135.7], "rewards": [] }],
      "forgery challenges": [],
      "domains": [],
      "misc": [{ "name": "Depths of Illusive Realm", "pos": [-194.3, 120.6], "rewards": [] }]
    },
    {
      "region": "Wuming Bay",
      "pos": [-124, 74],
      "subregions": [
        { "name": "Corroded Ruins", "pos": [-136.85, 60.64] },
        { "name": "Remnant Residence", "pos": [-168.15, 83.03] },
        { "name": "Shattered Blocks", "pos": [-132.6, 76.66] }
      ],
      "nexuses": [[-143.95, 67.16]],
      "beacons": [
        [-194.92, 49.34],
        [-174.2, 61.9],
        [-157.3, 57.3],
        [-146.3, 50.6],
        [-127.37, 57.84]
      ],
      "bosses": [{ "name": "Lampylumen Myriad", "pos": [-146.6, 48.2], "rewards": [] }],
      "tacet fields": [{ "pos": [-150.7, 54.4], "rewards": [] }],
      "tactical holograms": [{ "name": "Impermanence Heron", "pos": [-151, 56.4], "rewards": [] }],
      "forgery challenges": [{ "name": "Eroded Ruins", "pos": [-154.75, 68.7], "rewards": [] }],
      "domains": [],
      "misc": []
    }
  ]
}
